<?xml version="1.0" encoding="utf-8" ?>
<InputVar>

  <!--

    Element var:
      - identifikátor
        atribut id="neco"
      - funkce
        nepovinný atribut fn="název funkce"
      - proměnná
        nepovinný atribut var="název proměnné"
      - je proměnná cachovatelná?
        nepovinný atribut cacheable="[true|false]"
        výchozí hodnota je true
      - nepovinný atribut required="required"
        aplikuje se v případě použití uživatelské editace (níže)

    Element fn:
      - identifikátor (atribut id="neco")
      - funkce (atribut fn="název funkce")

    Dostupné funkce:
      - hash ... vrací otisk textu dle (nepovinného) atributu algo
        Formát podle http://php.net/manual/en/function.hash-algos.php
        Výchozím algoritmem je crc32b
      - strftime ... formátuje datum podle (nepovinného) atributu format
        Formát podle http://php.net/manual/en/function.strftime.php
        Výchozím formátem je %m/%d/%Y
      - sprintf ... formátuje obsah resp. elementy podle obsahu
        Formát podle http://php.net/manual/en/function.sprintf.php
      - replace ... nahrazuje obsah elementu podle obsažených elementů data
        Např. <data name="a">b</data> nahradí všechny "a" v textu za "b"
      - sequence ... řetězí volání funkcí uvedených v elementech call

  -->

  <fn id="months" fn="replace">
    <data name="[01]">ledna</data>
    <data name="[02]">února</data>
    <data name="[03]">března</data>
    <data name="[04]">dubna</data>
    <data name="[05]">května</data>
    <data name="[06]">června</data>
    <data name="[07]">července</data>
    <data name="[08]">srpna</data>
    <data name="[09]">září</data>
    <data name="[10]">října</data>
    <data name="[11]">listopadu</data>
    <data name="[12]">prosince</data>
  </fn>
  <fn id="yearformat" fn="strftime" format="%Y"/>
  <fn id="tmpdateformat" fn="strftime" format="%e. [%m] %Y"/>
  <fn id="dateformat" fn="sequence">
    <call>tmpdateformat</call>
    <call>months</call>
  </fn>

  <var id="nodebug">Provozní režim</var>
  <var id="debug">Ladící režim</var>
  <var id="servercache">Smazat mezipaměť serveru</var>
  <var id="filecache">Aktualizovat souborovou mezipaměť</var>
  <var id="reportbug"><a href="https://bitbucket.org/igwr/cms/issues?status=new&amp;status=open">Odeslat zpětnou vazbu</a></var>
  <!-- <var id="igcms"><a href="https://dokumenty.internetguru.cz/igcms">Specifikace IGCMS</a></var> -->
  <var id="codemirror"><a href="https://dokumenty.internetguru.cz/zkratky">Klávesové zkratky CodeMirror</a></var>
  <var id="version_link"><a href="/%s.php" var="cms-default_release@href" title="Pro nezávislé ladění zdrojových souborů (CSS/JS)">Samostatná větev</a></var>
  <!--<var id="service_plain">E-Základna, www.e-zakladna.cz</var>-->
  <!--<var id="service">Na službě: <a href="https://www.e-zakladna.cz/">E-Základna</a></var>-->
  <var id="service_plain">Nestárnoucí weby, www.nestarnouciweby.cz</var>
  <var id="service">Na službě: <a href="https://www.nestarnouciweby.cz/">Nestárnoucí weby</a></var>
  <var id="resp">Webmaster: <span var="cms-resp">n/a</span></var>
  <var id="mtime" cacheable="false">Úpravy webu: <span var="cms-mtime" fn="inputvar-dateformat">n/a</span></var>
  <var id="admin">Admin: <span var="cms-admin_id">n/a</span></var>
  <var id="cyear" fn="yearformat" var="cms-ctime" cacheable="false"/>
  <var id="year" fn="yearformat" var="cms-server" cacheable="false">now</var><!-- cms-server to disable value for webdiff -->
  <var id="today" fn="dateformat" var="cms-server" cacheable="false">now</var><!-- cms-server to disable value for webdiff -->
  <var id="adminmenu">
    <ul class="adminmenu noprint">
      <li><a href="?admin">Administrace</a></li>
      <li><a href="?log">Logy</a></li>
      <li><a href="?changelog">Historie verzí</a></li>
      <li><a href="?import">Import</a></li>
    </ul>
  </var>
  <var id="ielt7">
    <div class="ielte7" style="background: yellow; margin: 0; border: 0.3em solid red;">
      <dl>
        <dt>Používáte zastaralou verzi prohlížeče!</dt>
        <dd><a href="https://support.microsoft.com/cs-cz/help/17621/internet-explorer-downloads">Aktualizujte</a> na vyšší verzi,</dd>
        <dd>nainstalujte <a href="https://www.google.com/chrome/">alternativní prohlížeč</a> nebo</dd>
        <dd>kontaktujte správce svého počítače.</dd>
      </dl>
    </div>
  </var>


  <!--

    Uživatelská editace

    1) Element set
      - atribut type: select | text | textarea
      - atribut for: jaké proměnné se mají editovat
        - jeden nebo více regulárních výrazů oddělených mezerou
      - hodnota elementu: název skupiny

    a) Typ select
      - atribut datalist: proměnné, jejichž hodnoty mohou editované proměnné nabývat
        - jeden nebo více regulárních výrazů oddělených mezerou

    Například: 2 akce mohou nabývat hodnot a1, a2, a3 nebo empty

      <var id="empty"/>
      <var id="a1">K nákupu káva zdarma</var>
      <var id="a2">Sleva na vybrané zboží 50 %</var>
      <var id="a3">Rozvoz po Praza zdarma</var>

      <var id="akce1" var="empty">Akce 1</var>
      <var id="akce2" var="empty">Akce 2</var>
      <set type="select" for="akce\d " datalist="a\d+ empty">Akce</set>

    b) Typ text | textarea
      - atribut placeholder (nepovinný)
      - atribut pattern (nepovinný)

    Například:

      <var id="akce1">Nanuk Míša, 12 Kč (sleva 15 %)</var>
      <var id="akce2">Sušenky BeBe, 19 Kč (sleva 25 %)</var>
      <set type="text" for="akce\d+"
        pattern=".[5,20], \d\d Kč \(sleva \d\d %\)"
        placeholder="Čokoláda Orion, 22 Kč (sleva 20 %)">Akce</set>

    2) Element passwd (volitelný)
      - attribut username
      - zabezpečení formuláře pomocí vlastního hesla
        - otisk hesla vytvořený funkcí crypt (například příkazem "openssl passwd -1")

    Například:

      <passwd username="admin">$1$uvMgWfZe$MZGyiPRqL.YUDT3Jmurya0</passwd>

   -->

</InputVar>
